investhelper/__init__.py
investhelper/__main__.py
investhelper/proc.py
investhelper-0.1.1.dist-info/METADATA
investhelper-0.1.1.dist-info/WHEEL
investhelper-0.1.1.dist-info/entry_points.txt
investhelper-0.1.1.dist-info/top_level.txt
investhelper-0.1.1.dist-info/RECORD
