Metadata-Version: 2.1
Name: investhelper
Version: 0.1.1
Summary: A package for calculating profit and ROI
Author-email: Dusya <Lev.khrobostov@mail.ru>
License: MIT
